pytest_response/__init__.py
pytest_response/_version.py
pytest_response/app.py
pytest_response/database.py
pytest_response/exceptions.py
pytest_response/logger.py
pytest_response/plugin.py
pytest_response/interceptors/__init__.py
pytest_response/interceptors/_urllib.py
pytest_response/interceptors/_urllib3.py
pytest_response/interceptors/aiohttp.py
pytest_response/interceptors/requests.py
pytest_response/interceptors/urllib.py
pytest_response/interceptors/urllib3.py
pytest_remote_response-2.1.2.dist-info/LICENSE
pytest_remote_response-2.1.2.dist-info/METADATA
pytest_remote_response-2.1.2.dist-info/WHEEL
pytest_remote_response-2.1.2.dist-info/entry_points.txt
pytest_remote_response-2.1.2.dist-info/top_level.txt
pytest_remote_response-2.1.2.dist-info/RECORD
