Metadata-Version: 2.1
Name: pytest-remote-response
Version: 2.1.2
Summary: Pytest plugin for capturing and mocking connection requests.
Home-page: https://github.com/devanshshukla99/pytest-remote-response
Author: devanshshukla99
Author-email: devanshshukla99@outlook.com
License: MIT
Platform: UNKNOWN
Classifier: Development Status :: 5 - Production/Stable
Classifier: Framework :: Pytest
Classifier: Intended Audience :: Developers
Classifier: License :: OSI Approved :: MIT License
Classifier: Operating System :: OS Independent
Classifier: Programming Language :: Python
Classifier: Programming Language :: Python :: 3
Classifier: Programming Language :: Python :: 3 :: Only
Classifier: Programming Language :: Python :: 3.7
Classifier: Programming Language :: Python :: 3.8
Classifier: Programming Language :: Python :: 3.9
Classifier: Topic :: Software Development :: Testing
Classifier: Topic :: Utilities
Requires-Python: >=3.7
Requires-Dist: pytest (>=4.6)
Requires-Dist: requests (>=2.25.1)
Requires-Dist: aiohttp
Provides-Extra: docs
Requires-Dist: sphinx (==4.0.2) ; extra == 'docs'
Requires-Dist: sphinx-automodapi (==0.13) ; extra == 'docs'
Requires-Dist: sphinx-changelog (>=1.1.0rc1) ; extra == 'docs'
